README.md
setup.py
statistical_distributions5/Binomialdistribution.py
statistical_distributions5/Gaussiandistribution.py
statistical_distributions5/Generaldistribution.py
statistical_distributions5/__init__.py
statistical_distributions5.egg-info/PKG-INFO
statistical_distributions5.egg-info/SOURCES.txt
statistical_distributions5.egg-info/dependency_links.txt
statistical_distributions5.egg-info/not-zip-safe
statistical_distributions5.egg-info/top_level.txt